<?xml version="1.0" encoding="UTF-8"?>
<!DOCTYPE configuration>
<configuration>
  <verbose>true</verbose>
  <threads>4</threads>
  <mutators>
    <mutator>ALL</mutator>
  </mutators>
  <classPath>
    <entry>target/classes</entry>
    <entry>randoop-compiled</entry>
  </classPath>
  <targetClasses>
    <targetClass>com.company.*</targetClass>
  </targetClasses>
  <targetTests>
    <targetTest>RegressionTest*</targetTest>
    <targetTest>ErrorTest*</targetTest>
  </targetTests>
  <avoidCallsTo>
    <avoidCallsTo>java.util.logging</avoidCallsTo>
    <avoidCallsTo>org.apache.log4j</avoidCallsTo>
    <avoidCallsTo>org.slf4j</avoidCallsTo>
    <avoidCallsTo>org.apache.commons.logging</avoidCallsTo>
  </avoidCallsTo>
  <outputFormats>
    <outputFormat>HTML</outputFormat>
    <outputFormat>XML</outputFormat>
  </outputFormats>
  <timestampedReports>false</timestampedReports>
  <reportDir>target/pit-reports-randoop</reportDir>
</configuration> 